aprsd_webchat_extension/__init__.py
aprsd_webchat_extension/extension.py
aprsd_webchat_extension/utils.py
aprsd_webchat_extension/cmds/__init__.py
aprsd_webchat_extension/cmds/webchat.py
aprsd_webchat_extension/conf/__init__.py
aprsd_webchat_extension/conf/main.py
aprsd_webchat_extension/conf/opts.py
aprsd_webchat_extension/web/.DS_Store
aprsd_webchat_extension/web/__init__.py
aprsd_webchat_extension/web/chat/.DS_Store
aprsd_webchat_extension/web/chat/static/.DS_Store
aprsd_webchat_extension/web/chat/static/css/.DS_Store
aprsd_webchat_extension/web/chat/static/css/chat.css
aprsd_webchat_extension/web/chat/static/css/index.css
aprsd_webchat_extension/web/chat/static/css/style.css.map
aprsd_webchat_extension/web/chat/static/css/tabs.css
aprsd_webchat_extension/web/chat/static/css/upstream/.DS_Store
aprsd_webchat_extension/web/chat/static/css/upstream/bootstrap.min.css
aprsd_webchat_extension/web/chat/static/css/upstream/font.woff2
aprsd_webchat_extension/web/chat/static/css/upstream/google-fonts.css
aprsd_webchat_extension/web/chat/static/css/upstream/jquery-ui.css
aprsd_webchat_extension/web/chat/static/css/upstream/jquery.toast.css
aprsd_webchat_extension/web/chat/static/css/upstream/themes/default/assets/fonts/LatoLatin-Bold.woff
aprsd_webchat_extension/web/chat/static/css/upstream/themes/default/assets/fonts/LatoLatin-Bold.woff2
aprsd_webchat_extension/web/chat/static/css/upstream/themes/default/assets/fonts/LatoLatin-Regular.woff
aprsd_webchat_extension/web/chat/static/css/upstream/themes/default/assets/fonts/LatoLatin-Regular.woff2
aprsd_webchat_extension/web/chat/static/css/upstream/themes/default/assets/fonts/icons.woff
aprsd_webchat_extension/web/chat/static/css/upstream/themes/default/assets/fonts/icons.woff2
aprsd_webchat_extension/web/chat/static/css/upstream/themes/default/assets/fonts/outline-icons.woff
aprsd_webchat_extension/web/chat/static/css/upstream/themes/default/assets/fonts/outline-icons.woff2
aprsd_webchat_extension-1.2.3.dist-info/licenses/LICENSE
aprsd_webchat_extension-1.2.3.dist-info/METADATA
aprsd_webchat_extension-1.2.3.dist-info/WHEEL
aprsd_webchat_extension-1.2.3.dist-info/entry_points.txt
aprsd_webchat_extension-1.2.3.dist-info/top_level.txt
aprsd_webchat_extension-1.2.3.dist-info/RECORD
