Metadata-Version: 2.4
Name: aprsd-webchat-extension
Version: 1.2.3
Summary: APRSD Webchat
Author-email: "Walter A. Boring IV" <waboring@hemna.com>
Maintainer-email: "Walter A. Boring IV" <waboring@hemna.com>
License: 
Keywords: aprs,aprs-is,aprsd,aprsd-server,aprsd-client,aprsd-socket,aprsd-socket-server,aprsd-socket-client
Classifier: Development Status :: 5 - Production/Stable
Classifier: Environment :: Console
Classifier: Intended Audience :: Developers
Classifier: Intended Audience :: End Users/Desktop
Classifier: Intended Audience :: Information Technology
Classifier: Topic :: Communications :: Ham Radio
Classifier: Topic :: Internet
Classifier: Programming Language :: Python :: 3 :: Only
Classifier: Programming Language :: Python :: 3
Classifier: Programming Language :: Python :: 3.8
Classifier: Programming Language :: Python :: 3.9
Classifier: Programming Language :: Python :: 3.10
Classifier: Programming Language :: Python :: 3.11
Requires-Python: >=3.8
License-File: LICENSE
Requires-Dist: aprsd>=4.2.1
Requires-Dist: click
Requires-Dist: flask
Requires-Dist: flask-httpauth
Requires-Dist: flask-socketio
Requires-Dist: haversine
Requires-Dist: oslo_config
Requires-Dist: python-socketio
Provides-Extra: dev
Requires-Dist: pip; extra == "dev"
Requires-Dist: pip-tools; extra == "dev"
Requires-Dist: bump2version; extra == "dev"
Requires-Dist: wheel; extra == "dev"
Requires-Dist: watchdog; extra == "dev"
Requires-Dist: tox; extra == "dev"
Requires-Dist: Sphinx; extra == "dev"
Requires-Dist: twine; extra == "dev"
Dynamic: license-file
